mpmsub/__init__.py
mpmsub/cluster.py
mpmsub/utils.py
mpmsub-2025.10.16.dist-info/licenses/LICENSE
mpmsub-2025.10.16.dist-info/METADATA
mpmsub-2025.10.16.dist-info/WHEEL
mpmsub-2025.10.16.dist-info/top_level.txt
mpmsub-2025.10.16.dist-info/RECORD
